crackomatic/__init__.py
crackomatic/__main__.py
crackomatic/_version.py
crackomatic/args.py
crackomatic/audit.py
crackomatic/backend.py
crackomatic/cert.py
crackomatic/config.py
crackomatic/constants.py
crackomatic/cracker.py
crackomatic/email.py
crackomatic/flask.py
crackomatic/forms.py
crackomatic/job.py
crackomatic/ldap.py
crackomatic/log.py
crackomatic/models.py
crackomatic/reports.py
crackomatic/smb.py
crackomatic/user.py
Crack_O_Matic-0.0.dist-info/LICENSE
Crack_O_Matic-0.0.dist-info/METADATA
Crack_O_Matic-0.0.dist-info/WHEEL
Crack_O_Matic-0.0.dist-info/entry_points.txt
Crack_O_Matic-0.0.dist-info/top_level.txt
Crack_O_Matic-0.0.dist-info/RECORD
