Metadata-Version: 2.1
Name: Crack-O-Matic
Version: 0.0
Summary: Find and notify users in your Active Directory with weak passwords
Home-page: https://github.com/AdrianVollmer/Crack-O-Matic
Author: Adrian Vollmer
License: UNKNOWN
Project-URL: Read The Docs, https://crack-o-matic.readthedocs.io
Project-URL: Issue Tracker, https://github.com/AdrianVollmer/Crack-O-Matic/issues
Platform: UNKNOWN
Classifier: Programming Language :: Python :: 3
Classifier: License :: OSI Approved :: MIT License
Requires-Python: >=3.6
Requires-Dist: flask
Requires-Dist: flask-login
Requires-Dist: flask-wtf
Requires-Dist: flask-migrate
Requires-Dist: gevent
Requires-Dist: sqlalchemy
Requires-Dist: matplotlib
Requires-Dist: wtforms
Requires-Dist: ldap3
Requires-Dist: argon2-cffi
Requires-Dist: babel
Provides-Extra: tests
Requires-Dist: pytest ; extra == 'tests'
Requires-Dist: pytest-dotenv ; extra == 'tests'
Requires-Dist: python-dotenv ; extra == 'tests'
Requires-Dist: python-ldap ; extra == 'tests'
